{"cameraMode":{"drawMode":0,"name":"Shaded","section":"Shading Mode"},"sceneLighting":false,"audioPlay":false,"sceneViewState":{"m_AlwaysRefresh":false,"showFog":true,"showSkybox":false,"showFlares":true,"showImageEffects":true,"showParticleSystems":true,"showVisualEffectGraphs":true,"m_FxEnabled":true},"in2DMode":false,"pivot":{"x":-15.106193542480469,"y":0.869045615196228,"z":0.022097602486610414},"rotation":{"x":-0.22623583674430848,"y":0.028337977826595308,"z":-0.006584609858691692,"w":-0.973638653755188},"size":2.957064628601074,"orthographic":false}